pyroe/ProcessedQuant.py
pyroe/__init__.py
pyroe/convert.py
pyroe/fetch_processed_quant.py
pyroe/id_to_name.py
pyroe/load_fry.py
pyroe/load_processed_quant.py
pyroe/make_splici_txome.py
pyroe/make_txome.py
pyroe/pyroe_utils.py
pyroe/data/available_datasets.tsv
pyroe-0.9.3.data/scripts/pyroe
pyroe-0.9.3.dist-info/LICENSE
pyroe-0.9.3.dist-info/METADATA
pyroe-0.9.3.dist-info/WHEEL
pyroe-0.9.3.dist-info/top_level.txt
pyroe-0.9.3.dist-info/RECORD
