Metadata-Version: 2.1
Name: pyroe
Version: 0.9.3
Summary: utilities of alevin-fry
Home-page: https://github.com/COMBINE-lab/pyroe
Author: Dongze He, Rob Patro
Author-email: dhe17@umd.edu, rob@cs.umd.edu
Classifier: Programming Language :: Python :: 3
Classifier: License :: OSI Approved :: BSD License
Classifier: Operating System :: OS Independent
Requires-Python: >=3.7
License-File: LICENSE
Requires-Dist: pandas (<2.0.0,>=1.3.0)
Requires-Dist: pyranges (==0.0.120)
Requires-Dist: biopython (>=1.77)
Requires-Dist: packaging (>=21.0)
Requires-Dist: scanpy (>=1.8.2)
